ionic/__init__.py
ionic/sdk.py
ionic/sdkconfiguration.py
ionic/models/__init__.py
ionic/models/components/__init__.py
ionic/models/components/link.py
ionic/models/components/message.py
ionic/models/components/messagerole.py
ionic/models/components/messagetype.py
ionic/models/components/product.py
ionic/models/components/query.py
ionic/models/components/queryapirequest.py
ionic/models/components/queryapiresponse.py
ionic/models/components/queryresult.py
ionic/models/components/security.py
ionic/models/components/session.py
ionic/models/components/validationerror.py
ionic/models/errors/__init__.py
ionic/models/errors/httpvalidationerror.py
ionic/models/errors/sdkerror.py
ionic/models/operations/__init__.py
ionic/models/operations/query.py
ionic/utils/__init__.py
ionic/utils/retries.py
ionic/utils/utils.py
Ionic_API_SDK-0.9.3.dist-info/LICENSE.md
Ionic_API_SDK-0.9.3.dist-info/METADATA
Ionic_API_SDK-0.9.3.dist-info/WHEEL
Ionic_API_SDK-0.9.3.dist-info/top_level.txt
Ionic_API_SDK-0.9.3.dist-info/RECORD
